nextbrain/__init__.py
nextbrain/nextbrain.py
nextbrain-1.1.0.dist-info/METADATA
nextbrain-1.1.0.dist-info/WHEEL
nextbrain-1.1.0.dist-info/LICENSE
nextbrain-1.1.0.dist-info/RECORD
