Metadata-Version: 2.1
Name: nextbrain
Version: 1.1.0
Summary: Convenient access to the NextBrain API from python
Home-page: https://github.com/NextBrain-ai/nextbrain-python
License: LICENSE
Author: Softpoint Consultores S.L.
Author-email: info@softpoint.es
Requires-Python: >=3.7,<4.0
Classifier: License :: Other/Proprietary License
Classifier: Programming Language :: Python :: 3
Classifier: Programming Language :: Python :: 3.7
Classifier: Programming Language :: Python :: 3.8
Classifier: Programming Language :: Python :: 3.9
Classifier: Programming Language :: Python :: 3.10
Classifier: Programming Language :: Python :: 3.11
Project-URL: Repository, https://github.com/NextBrain-ai/nextbrain-python
